testwise.py
testwise-0.0.63.dist-info/LICENSE.txt
testwise-0.0.63.dist-info/METADATA
testwise-0.0.63.dist-info/WHEEL
testwise-0.0.63.dist-info/top_level.txt
testwise-0.0.63.dist-info/RECORD
