Metadata-Version: 2.1
Name: testwise
Version: 0.0.63
Summary: A backtester (backtest helper) for testing my trading strategies.
Home-page: https://github.com/aticio/testwise
Author: Özgür Atıcı
Author-email: aticiozgur@gmail.com
License: UNKNOWN
Platform: UNKNOWN
Classifier: Programming Language :: Python :: 3
Classifier: License :: OSI Approved :: MIT License
Classifier: Operating System :: OS Independent
Requires-Dist: matplotlib
Provides-Extra: dev
Requires-Dist: pytest (>=3.7) ; extra == 'dev'
